fp_arithmatic/__init__.py
fp_arithmatic/add.py
fp_arithmatic/distance.py
fp_arithmatic/dot.py
fp_arithmatic/mul.py
fp_arithmatic/sqrt.py
fp_arithmatic-1.0.0.dist-info/METADATA
fp_arithmatic-1.0.0.dist-info/WHEEL
fp_arithmatic-1.0.0.dist-info/top_level.txt
fp_arithmatic-1.0.0.dist-info/RECORD
