Metadata-Version: 2.1
Name: fp-arithmatic
Version: 1.0.0
Summary: A simple arithmatic library
Home-page: UNKNOWN
Author: Faizan Patel
License: MIT
Platform: UNKNOWN
Requires-Python: >=3.6
Requires-Dist: numpy
